pydsql/__init__.py
pydsql/generator.py
pydsql-0.1.4.dist-info/licenses/LICENSE
pydsql-0.1.4.dist-info/METADATA
pydsql-0.1.4.dist-info/WHEEL
pydsql-0.1.4.dist-info/top_level.txt
pydsql-0.1.4.dist-info/RECORD
